breakneck/__init__.py
breakneck/adjacency_graph.py
breakneck/cli.py
breakneck/conversions.py
breakneck/footprint.py
breakneck/test_polyfinder.py
breakneck/track.py
breakneck-0.3.0.dist-info/METADATA
breakneck-0.3.0.dist-info/WHEEL
breakneck-0.3.0.dist-info/entry_points.txt
breakneck-0.3.0.dist-info/licenses/LICENSE
breakneck-0.3.0.dist-info/RECORD
