Metadata-Version: 2.4
Name: breakneck
Version: 0.3.0
Summary: Stitching via visualization and manual forced neckdowns for KiCad
Project-URL: Homepage, https://github.com/hatlabs/breakneck
Author-email: Matti Airas <matti.airas@hatlabs.fi>
License-Expression: MIT
License-File: LICENSE
Keywords: EDA,KiCad,PCB,breakneck,neckdown,stitching
Classifier: Development Status :: 4 - Beta
Classifier: License :: OSI Approved :: MIT License
Classifier: Programming Language :: Python :: 3
Classifier: Topic :: Scientific/Engineering :: Electronic Design Automation (EDA)
Classifier: Topic :: Utilities
Requires-Python: >=3.11
Requires-Dist: kicad-python>=0.2.0
Requires-Dist: loguru>=0.7.2
Requires-Dist: shapely>=2.0.7
Requires-Dist: svgpathtools>=1.6.1
